odoo/addons/partner_supplierinfo_smartbutton/README.rst
odoo/addons/partner_supplierinfo_smartbutton/__init__.py
odoo/addons/partner_supplierinfo_smartbutton/__manifest__.py
odoo/addons/partner_supplierinfo_smartbutton/i18n/es.po
odoo/addons/partner_supplierinfo_smartbutton/i18n/es_419.po
odoo/addons/partner_supplierinfo_smartbutton/i18n/fr.po
odoo/addons/partner_supplierinfo_smartbutton/i18n/it.po
odoo/addons/partner_supplierinfo_smartbutton/i18n/partner_supplierinfo_smartbutton.pot
odoo/addons/partner_supplierinfo_smartbutton/models/__init__.py
odoo/addons/partner_supplierinfo_smartbutton/models/res_partner.py
odoo/addons/partner_supplierinfo_smartbutton/readme/CONFIGURE.md
odoo/addons/partner_supplierinfo_smartbutton/readme/CONTRIBUTORS.md
odoo/addons/partner_supplierinfo_smartbutton/readme/DESCRIPTION.md
odoo/addons/partner_supplierinfo_smartbutton/readme/INSTALL.md
odoo/addons/partner_supplierinfo_smartbutton/readme/USAGE.md
odoo/addons/partner_supplierinfo_smartbutton/static/description/icon.png
odoo/addons/partner_supplierinfo_smartbutton/static/description/index.html
odoo/addons/partner_supplierinfo_smartbutton/tests/__init__.py
odoo/addons/partner_supplierinfo_smartbutton/tests/test_partner_supplierinfo_smartbutton.py
odoo/addons/partner_supplierinfo_smartbutton/views/res_partner_view.xml
odoo_addon_partner_supplierinfo_smartbutton-18.0.1.0.0.2.dist-info/METADATA
odoo_addon_partner_supplierinfo_smartbutton-18.0.1.0.0.2.dist-info/WHEEL
odoo_addon_partner_supplierinfo_smartbutton-18.0.1.0.0.2.dist-info/top_level.txt
odoo_addon_partner_supplierinfo_smartbutton-18.0.1.0.0.2.dist-info/RECORD
